chartree/__init__.py
chartree/tree.py
treescharacter/__init__.py
treescharacter/tree.py
chartree-0.1.0.dist-info/LICENSE
chartree-0.1.0.dist-info/METADATA
chartree-0.1.0.dist-info/WHEEL
chartree-0.1.0.dist-info/top_level.txt
chartree-0.1.0.dist-info/RECORD
