Metadata-Version: 2.1
Name: chartree
Version: 0.1.0
Summary: Grow trees
Home-page: https://github.com/bsmrvl/a-trees-character
Author: bsmrvl
Author-email: ben.j.somerville@icloud.com
License: UNKNOWN
Platform: UNKNOWN
Classifier: Programming Language :: Python :: 3
Classifier: License :: OSI Approved :: MIT License
Classifier: Operating System :: OS Independent
Requires-Python: >=3.6
Requires-Dist: numpy
Requires-Dist: IPython
